dispatches_data/packages/dynamic_sweep/COPYRIGHT.md
dispatches_data/packages/dynamic_sweep/LICENSE.md
dispatches_data/packages/dynamic_sweep/README.md
dispatches_data/packages/dynamic_sweep/__init__.py
dispatches_data/packages/dynamic_sweep/FE/Dispatch_generator_data_FE_separate_whole.csv
dispatches_data/packages/dynamic_sweep/FE/Dispatch_storage_data_FE_separate_whole.csv
dispatches_data/packages/dynamic_sweep/FE/FE_revenue.csv
dispatches_data/packages/dynamic_sweep/FE/sweep_parameters_results_FE_whole.h5
dispatches_data/packages/dynamic_sweep/FE/input_data/sweep_parameters_10_1000.csv
dispatches_data/packages/dynamic_sweep/FE/input_data/sweep_parameters_10_500.csv
dispatches_data/packages/dynamic_sweep/FE/input_data/sweep_parameters_15_1000.csv
dispatches_data/packages/dynamic_sweep/FE/input_data/sweep_parameters_15_500.csv
dispatches_data/packages/dynamic_sweep/FE/results_fossil_sweep_10_1000/sweep_results_index_0.csv
dispatches_data/packages/dynamic_sweep/FE/results_fossil_sweep_10_1000/sweep_results_index_1.csv
dispatches_data/packages/dynamic_sweep/FE/results_fossil_sweep_10_1000/sweep_results_index_10.csv
dispatches_data/packages/dynamic_sweep/FE/results_fossil_sweep_10_1000/sweep_results_index_11.csv
dispatches_data/packages/dynamic_sweep/FE/results_fossil_sweep_10_1000/sweep_results_index_12.csv
dispatches_data/packages/dynamic_sweep/FE/results_fossil_sweep_10_1000/sweep_results_index_13.csv
dispatches_data/packages/dynamic_sweep/FE/results_fossil_sweep_10_1000/sweep_results_index_14.csv
dispatches_data/packages/dynamic_sweep/FE/results_fossil_sweep_10_1000/sweep_results_index_15.csv
dispatches_data/packages/dynamic_sweep/FE/results_fossil_sweep_10_1000/sweep_results_index_16.csv
dispatches_data/packages/dynamic_sweep/FE/results_fossil_sweep_10_1000/sweep_results_index_17.csv
dispatches_data/packages/dynamic_sweep/FE/results_fossil_sweep_10_1000/sweep_results_index_18.csv
dispatches_dynamic_sweep_data-23.7.24.dist-info/METADATA
dispatches_dynamic_sweep_data-23.7.24.dist-info/WHEEL
dispatches_dynamic_sweep_data-23.7.24.dist-info/top_level.txt
dispatches_dynamic_sweep_data-23.7.24.dist-info/RECORD
