Metadata-Version: 2.1
Name: dispatches-dynamic-sweep-data
Version: 23.7.24
Requires-Dist: dispatches-data-packages
